[
  {
    "line": 1,
    "elements": [
      {
        "line": 3,
        "name": "",
        "description": "",
        "type": "background",
        "keyword": "Background",
        "steps": [
          {
            "result": {
              "duration": 4749000000,
              "status": "passed"
            },
            "before": [
              {
                "result": {
                  "status": "passed"
                },
                "match": {
                  "location": "stepDefinations.HookSD.beforeSteps()"
                }
              }
            ],
            "line": 4,
            "name": "login page",
            "match": {
              "location": "stepDefinations.BackgroundSD.login_page()"
            },
            "after": [
              {
                "result": {
                  "status": "passed"
                },
                "match": {
                  "location": "stepDefinations.HookSD.afterSteps()"
                }
              }
            ],
            "keyword": "Given "
          }
        ]
      },
      {
        "start_timestamp": "2023-01-17T13:35:51.140Z",
        "before": [
          {
            "result": {
              "duration": 6291000000,
              "status": "passed"
            },
            "match": {
              "location": "stepDefinations.BackgroundSD.setupBrowser()"
            }
          },
          {
            "result": {
              "duration": 1903000000,
              "status": "passed"
            },
            "match": {
              "location": "stepDefinations.HookSD.setupBrowser()"
            }
          }
        ],
        "line": 6,
        "name": "verify valid data",
        "description": "",
        "id": "checking-background;verify-valid-data",
        "after": [
          {
            "result": {
              "duration": 845000000,
              "status": "passed"
            },
            "match": {
              "location": "stepDefinations.BackgroundSD.tearDown1()"
            }
          },
          {
            "result": {
              "duration": 915000000,
              "status": "passed"
            },
            "match": {
              "location": "stepDefinations.HookSD.tearDown1()"
            }
          },
          {
            "result": {
              "status": "passed"
            },
            "match": {
              "location": "stepDefinations.HookSD.tearDown2()"
            }
          }
        ],
        "type": "scenario",
        "keyword": "Scenario",
        "steps": [
          {
            "result": {
              "duration": 995000000,
              "status": "passed"
            },
            "before": [
              {
                "result": {
                  "status": "passed"
                },
                "match": {
                  "location": "stepDefinations.HookSD.beforeSteps()"
                }
              }
            ],
            "line": 7,
            "name": "Enter data",
            "match": {
              "location": "stepDefinations.BackgroundSD.enter_data()"
            },
            "after": [
              {
                "result": {
                  "status": "passed"
                },
                "match": {
                  "location": "stepDefinations.HookSD.afterSteps()"
                }
              }
            ],
            "keyword": "When "
          },
          {
            "result": {
              "duration": 1394000000,
              "status": "passed"
            },
            "before": [
              {
                "result": {
                  "status": "passed"
                },
                "match": {
                  "location": "stepDefinations.HookSD.beforeSteps()"
                }
              }
            ],
            "line": 8,
            "name": "button",
            "match": {
              "location": "stepDefinations.BackgroundSD.button()"
            },
            "after": [
              {
                "result": {
                  "status": "passed"
                },
                "match": {
                  "location": "stepDefinations.HookSD.afterSteps()"
                }
              }
            ],
            "keyword": "Then "
          }
        ]
      },
      {
        "line": 3,
        "name": "",
        "description": "",
        "type": "background",
        "keyword": "Background",
        "steps": [
          {
            "result": {
              "duration": 3960000000,
              "status": "passed"
            },
            "before": [
              {
                "result": {
                  "status": "passed"
                },
                "match": {
                  "location": "stepDefinations.HookSD.beforeSteps()"
                }
              }
            ],
            "line": 4,
            "name": "login page",
            "match": {
              "location": "stepDefinations.BackgroundSD.login_page()"
            },
            "after": [
              {
                "result": {
                  "status": "passed"
                },
                "match": {
                  "location": "stepDefinations.HookSD.afterSteps()"
                }
              }
            ],
            "keyword": "Given "
          }
        ]
      },
      {
        "start_timestamp": "2023-01-17T13:36:08.413Z",
        "before": [
          {
            "result": {
              "duration": 1928000000,
              "status": "passed"
            },
            "match": {
              "location": "stepDefinations.BackgroundSD.setupBrowser()"
            }
          },
          {
            "result": {
              "duration": 1821000000,
              "status": "passed"
            },
            "match": {
              "location": "stepDefinations.HookSD.setupBrowser()"
            }
          }
        ],
        "line": 10,
        "name": "verify Wrong data",
        "description": "",
        "id": "checking-background;verify-wrong-data",
        "after": [
          {
            "result": {
              "duration": 824000000,
              "status": "passed"
            },
            "match": {
              "location": "stepDefinations.BackgroundSD.tearDown1()"
            }
          },
          {
            "result": {
              "duration": 777000000,
              "status": "passed"
            },
            "match": {
              "location": "stepDefinations.HookSD.tearDown1()"
            }
          },
          {
            "result": {
              "status": "passed"
            },
            "match": {
              "location": "stepDefinations.HookSD.tearDown2()"
            }
          }
        ],
        "type": "scenario",
        "keyword": "Scenario",
        "steps": [
          {
            "result": {
              "duration": 910000000,
              "status": "passed"
            },
            "before": [
              {
                "result": {
                  "status": "passed"
                },
                "match": {
                  "location": "stepDefinations.HookSD.beforeSteps()"
                }
              }
            ],
            "line": 11,
            "name": "Enter wrong data",
            "match": {
              "location": "stepDefinations.BackgroundSD.enter_wrong_data()"
            },
            "after": [
              {
                "result": {
                  "status": "passed"
                },
                "match": {
                  "location": "stepDefinations.HookSD.afterSteps()"
                }
              }
            ],
            "keyword": "When "
          },
          {
            "result": {
              "duration": 139000000,
              "status": "passed"
            },
            "before": [
              {
                "result": {
                  "status": "passed"
                },
                "match": {
                  "location": "stepDefinations.HookSD.beforeSteps()"
                }
              }
            ],
            "line": 12,
            "name": "button",
            "match": {
              "location": "stepDefinations.BackgroundSD.button()"
            },
            "after": [
              {
                "result": {
                  "status": "passed"
                },
                "match": {
                  "location": "stepDefinations.HookSD.afterSteps()"
                }
              }
            ],
            "keyword": "Then "
          }
        ]
      }
    ],
    "name": "Checking Background",
    "description": "",
    "id": "checking-background",
    "keyword": "Feature",
    "uri": "file:src/test/resources/Features/Background.feature",
    "tags": []
  }
]